odc/__init__.py
odc/clean_filtering_test.py
odc/connector.py
odc/count_northwind.py
odc/main.py
odc/test_northwind.py
odc/config/__init__.py
odc/config/models.py
odc/config/northwind_config.py
odc/config/sap_module_mapping.py
odc/connectors/__init__.py
odc/connectors/rest_connector.py
odc/connectors/streaming_connector.py
odc/error_handling/__init__.py
odc/error_handling/dead_letter_queue.py
odc/monitoring/__init__.py
odc/monitoring/metrics.py
odc/monitoring/prometheus_config.py
odc/planning/__init__.py
odc/planning/graph_builder.py
odc/planning/plan_generator.py
odc/planning/record_tracker.py
odc/services/__init__.py
odc/services/count.py
odc/services/metadata.py
odc/storage/__init__.py
odc/storage/bigquery_storage.py
odc/storage/gcs_storage.py
odc/storage/local_storage.py
odc/storage/transformer.py
odc/utils/__init__.py
odc/utils/log_messages.py
odc/utils/logging_config.py
odc/workers/__init__.py
odc/workers/proxy_pool.py
odc/workers/resilience.py
sap_odata_connector_testcov-1.0.1.dist-info/licenses/LICENSE
sap_odata_connector_testcov-1.0.1.dist-info/METADATA
sap_odata_connector_testcov-1.0.1.dist-info/WHEEL
sap_odata_connector_testcov-1.0.1.dist-info/top_level.txt
sap_odata_connector_testcov-1.0.1.dist-info/RECORD
