Metadata-Version: 2.4
Name: sap-odata-connector-testcov
Version: 1.0.1
Summary: A powerful Python library for connecting to SAP OData services
Home-page: https://github.com
Author: Bhuvan Chandra Mothe
Author-email: Bhuvan Chandra Mothe <bhuvan.dumpmail@gmail.com>
License: MIT
Project-URL: Homepage, https://github.com/yourusername/sap-odata-connector
Project-URL: Documentation, https://github.com/yourusername/sap-odata-connector/docs
Project-URL: Repository, https://github.com/yourusername/sap-odata-connector
Project-URL: Bug Tracker, https://github.com/yourusername/sap-odata-connector/issues
Keywords: sap,odata,connector,api,rest,data,integration,etl
Classifier: Development Status :: 4 - Beta
Classifier: Intended Audience :: Developers
Classifier: Topic :: Software Development :: Libraries :: Python Modules
Classifier: License :: OSI Approved :: MIT License
Classifier: Programming Language :: Python :: 3
Classifier: Programming Language :: Python :: 3.8
Classifier: Programming Language :: Python :: 3.9
Classifier: Programming Language :: Python :: 3.10
Classifier: Programming Language :: Python :: 3.11
Classifier: Programming Language :: Python :: 3.12
Requires-Python: >=3.8
License-File: LICENSE
Requires-Dist: aiohttp>=3.8.0
Requires-Dist: orjson>=3.9.0
Requires-Dist: structlog>=23.1.0
Requires-Dist: pydantic>=2.0.0
Requires-Dist: asyncio>=3.4.3
Requires-Dist: aiolimiter>=1.2.0
Requires-Dist: attrs>=25.0.0
Requires-Dist: coloredlogs>=14.0
Requires-Dist: cryptography>=45.0.0
Requires-Dist: dynaconf>=3.2.0
Requires-Dist: fastapi>=0.116.0
Requires-Dist: google-cloud-bigquery>=3.37.0
Requires-Dist: google-cloud-storage>=3.4.0
Requires-Dist: httpx>=0.28.0
Requires-Dist: lxml>=6.0.0
Requires-Dist: prometheus-client>=0.22.0
Requires-Dist: pybreaker>=1.4.0
Requires-Dist: pyodata>=1.11.0
Requires-Dist: python-dateutil>=2.9.0
Requires-Dist: python-dotenv>=1.1.0
Requires-Dist: PyYAML>=6.0.0
Requires-Dist: requests>=2.32.0
Requires-Dist: SQLAlchemy>=2.0.0
Requires-Dist: tenacity>=9.1.0
Requires-Dist: tqdm>=4.67.0
Requires-Dist: uvicorn>=0.36.0
Provides-Extra: dev
Requires-Dist: pytest>=7.0.0; extra == "dev"
Requires-Dist: pytest-asyncio>=0.21.0; extra == "dev"
Requires-Dist: black>=23.0.0; extra == "dev"
Requires-Dist: flake8>=6.0.0; extra == "dev"
Requires-Dist: mypy>=1.0.0; extra == "dev"
Provides-Extra: bigquery
Requires-Dist: google-cloud-bigquery>=3.0.0; extra == "bigquery"
Dynamic: author
Dynamic: home-page
Dynamic: license-file
Dynamic: requires-python
